labbench/__init__.py
labbench/_backends.py
labbench/_data.py
labbench/_device.py
labbench/_host.py
labbench/_rack.py
labbench/_serialize.py
labbench/_version.py
labbench/py.typed
labbench/util.py
labbench/cli/__init__.py
labbench/cli/__main__.py
labbench/paramattr/__init__.py
labbench/paramattr/_bases.py
labbench/paramattr/_key_adapters.py
labbench/paramattr/_types.py
labbench/paramattr/method.py
labbench/paramattr/method_kwarg.py
labbench/paramattr/property.py
labbench/paramattr/value.py
labbench/testing/__init__.py
labbench/testing/pyvisa_sim.py
labbench/testing/pyvisa_sim.yml
labbench/testing/store_backend.py
labbench-0.45.1.dist-info/METADATA
labbench-0.45.1.dist-info/WHEEL
labbench-0.45.1.dist-info/entry_points.txt
labbench-0.45.1.dist-info/licenses/LICENSE.md
labbench-0.45.1.dist-info/RECORD
