Metadata-Version: 2.1
Name: labbench
Version: 0.45.1
Summary: The `labbench` module provides API tools to support python scripting for laboratory automation.The goal is to simplify the process of developing an experimental procedure into clear, concise, explainable, and reusable code.
Project-URL: homepage, https://github.com/usnistgov/labbench
Project-URL: repository, https://github.com/usnistgov/labbench
Project-URL: documentation, https://pages.nist.gov/labbench
Project-URL: changelog, https://github.com/usnistgov/labbench/blob/master/ChangeLog.md
Author: Shane Allman, Paul Blanchard
Author-email: Dan Kuester <daniel.kuester@nist.gov>, Yao Ma <yao.ma@nist.gov>
Maintainer-email: Dan Kuester <daniel.kuester@nist.gov>
License: # License
License-File: LICENSE.md
Requires-Python: <3.14,>=3.9
Requires-Dist: click~=8.0
Requires-Dist: comtypes; sys_platform == 'win32'
Requires-Dist: dulwich>=0.20
Requires-Dist: feather-format>=0.4.0
Requires-Dist: libusb-package; sys_platform == 'win32'
Requires-Dist: libusb1>=3.1.0
Requires-Dist: numpy>=1.19
Requires-Dist: pandas<3,>=1.2.0
Requires-Dist: pip
Requires-Dist: psutil>=5.0
Requires-Dist: pyarrow>=14
Requires-Dist: pyserial>=3.0
Requires-Dist: pyvisa-py[gpib-ctypes,psutil,serial,usb]>=0.6
Requires-Dist: pyvisa-sim>=0.5.1
Requires-Dist: pyvisa>=1.8
Requires-Dist: pywin32; sys_platform == 'win32'
Requires-Dist: ruamel-yaml>=0.17.21
Requires-Dist: sqlalchemy<2,>=1.4
Requires-Dist: typing-extensions>=4.8.0
Requires-Dist: validators>=0.20.0
Provides-Extra: dev
Requires-Dist: ast-decompiler; extra == 'dev'
Requires-Dist: astor>=0.8.1; extra == 'dev'
Requires-Dist: ipykernel; extra == 'dev'
Requires-Dist: ipython; extra == 'dev'
Requires-Dist: pip; extra == 'dev'
Requires-Dist: ruff; extra == 'dev'
Requires-Dist: twine; extra == 'dev'
Provides-Extra: doc
Requires-Dist: jupytext>=1.6.0; extra == 'doc'
Requires-Dist: mypy-extensions>=1.0.0; extra == 'doc'
Requires-Dist: mypy>=1.7.0; extra == 'doc'
Requires-Dist: myst-nb>=1.0; extra == 'doc'
Requires-Dist: pyperf>=2.6.2; extra == 'doc'
Requires-Dist: sphinx>=7; extra == 'doc'
Requires-Dist: toml; extra == 'doc'
Provides-Extra: dotnet
Requires-Dist: pythonnet; extra == 'dotnet'
Provides-Extra: jupyter
Requires-Dist: ipython; extra == 'jupyter'
Requires-Dist: ipywidgets; extra == 'jupyter'
Requires-Dist: jupyter; extra == 'jupyter'
Requires-Dist: notebook; extra == 'jupyter'
Provides-Extra: pyvicp
Requires-Dist: pyvicp; extra == 'pyvicp'
Provides-Extra: pyvisa-py-extras
Requires-Dist: zeroconf; extra == 'pyvisa-py-extras'
